{"index.md":"6ce0b0ba","sponsor_index.md":"1a7b7c46","zh_base_com-events.md":"b09fe1e7","zh_base_custom.md":"978d5240","zh_base_index.md":"d987bf2f","zh_base_multiple-instances.md":"f2b85e29","zh_context-menu_index.md":"e5a408fd","zh_control_citylist.md":"3643217d","zh_control_copyright.md":"10dbf735","zh_control_custom.md":"6c50f8e2","zh_control_location.md":"54d413bd","zh_control_navigation3d.md":"ac0ff1da","zh_control_panorama-control.md":"6fd8330e","zh_control_scale.md":"bd33f477","zh_control_zoom.md":"c07c28ce","zh_expand_mapvgl.md":"163a03c2","zh_guide_config.md":"1cdf5f9b","zh_guide_quick-start.md":"32b2b6e1","zh_guide_usage-cdn.md":"c27b527f","zh_guide_usage-sfc.md":"6bc093a8","zh_hooks_useaddressgeocoder.md":"4efdd921","zh_hooks_useareaboundary.md":"c84e2802","zh_hooks_usebrowserlocation.md":"5a2679b8","zh_hooks_useiplocation.md":"5cd3c70c","zh_hooks_usepoint.md":"0c9e64a2","zh_hooks_usepointgeocoder.md":"758e4fea","zh_hooks_usetrackanimation.md":"28e67e13","zh_hooks_useviewanimation.md":"883c2852","zh_index.md":"9dc52fb9","zh_layer_panorama-coverage.md":"3221db4a","zh_overlay_beziercurve.md":"140b29c0","zh_overlay_circle.md":"c1275237","zh_overlay_ground-overlay.md":"d47ddf1e","zh_overlay_infowindow.md":"bd45d5e1","zh_overlay_label.md":"f19db4aa","zh_overlay_marker.md":"7f40b1c5","zh_overlay_marker3d.md":"9c04fa0d","zh_overlay_polygon.md":"53b409d1","zh_overlay_polyline.md":"a7b69939","zh_overlay_prism.md":"813e9057"}
